ninetails/__init__.py
ninetails/exceptions.py
ninetails/process_utils.py
ninetails/protocol.py
ninetails/pseudo_spv_gym_env.py
ninetails/spv_gym_env.py
ninetails-0.0.9.dist-info/METADATA
ninetails-0.0.9.dist-info/WHEEL
ninetails-0.0.9.dist-info/top_level.txt
ninetails-0.0.9.dist-info/RECORD
